dscigametrics/__init__.py
dscigametrics/compute_metrics.py
dscigametrics/daily_plot.py
dscigametrics/find_campaigns.py
dscigametrics/stat_summary.py
dscigametrics-0.0.0.dist-info/LICENSE
dscigametrics-0.0.0.dist-info/METADATA
dscigametrics-0.0.0.dist-info/WHEEL
dscigametrics-0.0.0.dist-info/RECORD
