Metadata-Version: 2.1
Name: dscigametrics
Version: 0.0.0
Summary: Computing Google Analytics Metrics!
License: MIT
Author: Beth Ou Yang, Ian MacCarthy, Weilin Han, Yili Tang
Requires-Python: >=3.9
Classifier: License :: OSI Approved :: MIT License
Classifier: Programming Language :: Python :: 3
Classifier: Programming Language :: Python :: 3.9
Classifier: Programming Language :: Python :: 3.10
Classifier: Programming Language :: Python :: 3.11
Classifier: Programming Language :: Python :: 3.12
Requires-Dist: altair (>=5.2.0)
Requires-Dist: numpy (>=1.26.3)
Requires-Dist: pandas (>=2.1.4)
